discord/ext/speedups/__init__.py
discord/ext/speedups/copus/__init__.py
discord/ext/speedups/copus/_copus.cp37-win32.pyd
discord/ext/speedups/copus/_setup.py
discord/ext/speedups/copus/copus.py
discord_ext_speedups-0.0.1.dist-info/LICENSE
discord_ext_speedups-0.0.1.dist-info/METADATA
discord_ext_speedups-0.0.1.dist-info/WHEEL
discord_ext_speedups-0.0.1.dist-info/top_level.txt
discord_ext_speedups-0.0.1.dist-info/RECORD
