Metadata-Version: 2.1
Name: discord-ext-speedups
Version: 0.0.1
Summary: Cython speedups for various parts of discord.py
Home-page: https://github.com/imayhaveborkedit/discord-ext-speedups
Author: Imayhaveborkedit
License: MIT
Project-URL: Code, https://github.com/imayhaveborkedit/discord-ext-speedups
Project-URL: Issue tracker, https://github.com/imayhaveborkedit/discord-ext-speedups/issues
Platform: UNKNOWN
Requires-Python: >=3.6.4
